{"id":"g34","name":"Meharry Medical College","verdict":"confirm","my_class":"regional","my_us_share":0.99,"my_region_shares":{"sub_saharan_africa":0,"south_asia":0,"east_asia_pacific":0,"latin_america_caribbean":0,"middle_east_north_africa":0,"europe_central_asia":0,"north_america_us":0.99,"global_unattributable":0.01},"key_evidence_url":"https://webarchive.mmc.edu/wp-content/uploads/2024/11/2024-2025-Academic-Catalog-MMC.pdf","note":"Current catalog locates core clinical operations in Tennessee and other US sites; international activity is mentioned but not quantified, so 1% remains unattributable."}
