{"id":"g36","name":"Digital Promise","verdict":"confirm","my_class":"us_inclusive_global","my_us_share":0.999,"my_region_shares":{"sub_saharan_africa":0,"south_asia":0,"east_asia_pacific":0,"latin_america_caribbean":0,"middle_east_north_africa":0,"europe_central_asia":0,"north_america_us":0.999,"global_unattributable":0.001},"key_evidence_url":"https://digitalpromise.org/wp-content/uploads/2025/11/2024-Exempt-Organization-Return-Digital-Promise-Global-Public-Disclosure-2.pdf","note":"Primary filings report only $51,000 of activity outside the U.S.; global programs exist, but their complete regional cost allocation is undisclosed."}
